[
  {
    "boostedShaderModifierType2": 0,
    "boostedShaderModifierType": 23,
    "boostedSizeModifierType": 0,
    "specificModifierChance": 85,
    "modifierChanceMultiplier": 2,
    "rareFishChance": 0.05,
    "luckMultiplier": 1,
    "spawnWeight": 1,
    "eventRadius": 15,
    "_source": "variablesjs_4790"
  },
  {
    "boostedShaderModifierType2": 0,
    "boostedShaderModifierType": 7,
    "boostedSizeModifierType": 0,
    "specificModifierChance": 85,
    "modifierChanceMultiplier": 2,
    "rareFishChance": 0,
    "luckMultiplier": 1,
    "spawnWeight": 100,
    "eventRadius": 15,
    "_source": "variablesjs_4996"
  },
  {
    "boostedShaderModifierType2": 0,
    "boostedShaderModifierType": 21,
    "boostedSizeModifierType": 0,
    "specificModifierChance": 85,
    "modifierChanceMultiplier": 2,
    "rareFishChance": 0,
    "luckMultiplier": 1.5,
    "spawnWeight": 100,
    "eventRadius": 15,
    "_source": "variablesjs_4999"
  },
  {
    "boostedShaderModifierType2": 15,
    "boostedShaderModifierType": 14,
    "boostedSizeModifierType": 0,
    "specificModifierChance": 85,
    "modifierChanceMultiplier": 2,
    "rareFishChance": 0,
    "luckMultiplier": 1.5,
    "spawnWeight": 100,
    "eventRadius": 15,
    "_source": "variablesjs_5119"
  },
  {
    "boostedShaderModifierType2": 0,
    "boostedShaderModifierType": 6,
    "boostedSizeModifierType": 0,
    "specificModifierChance": 85,
    "modifierChanceMultiplier": 2,
    "rareFishChance": 0.8,
    "luckMultiplier": 1,
    "spawnWeight": 1,
    "eventRadius": 15,
    "_source": "variablesjs_5142"
  },
  {
    "boostedShaderModifierType2": 0,
    "boostedShaderModifierType": 3,
    "boostedSizeModifierType": 0,
    "specificModifierChance": 85,
    "modifierChanceMultiplier": 2,
    "rareFishChance": 0.8,
    "luckMultiplier": 1,
    "spawnWeight": 1,
    "eventRadius": 15,
    "_source": "variablesjs_5259"
  },
  {
    "boostedShaderModifierType2": 0,
    "boostedShaderModifierType": 9,
    "boostedSizeModifierType": 0,
    "specificModifierChance": 85,
    "modifierChanceMultiplier": 2,
    "rareFishChance": 0,
    "luckMultiplier": 1,
    "spawnWeight": 100,
    "eventRadius": 15,
    "_source": "variablesjs_5435"
  },
  {
    "boostedShaderModifierType2": 0,
    "boostedShaderModifierType": 2,
    "boostedSizeModifierType": 0,
    "specificModifierChance": 85,
    "modifierChanceMultiplier": 2,
    "rareFishChance": 0,
    "luckMultiplier": 1.5,
    "spawnWeight": 100,
    "eventRadius": 15,
    "_source": "variablesjs_5517"
  },
  {
    "boostedShaderModifierType2": 0,
    "boostedShaderModifierType": 0,
    "boostedSizeModifierType": 1,
    "specificModifierChance": 85,
    "modifierChanceMultiplier": 1.5,
    "rareFishChance": 0.8,
    "luckMultiplier": 2,
    "spawnWeight": 1,
    "eventRadius": 15,
    "_source": "variablesjs_5594"
  },
  {
    "boostedShaderModifierType2": 0,
    "boostedShaderModifierType": 0,
    "boostedSizeModifierType": 0,
    "specificModifierChance": 0,
    "modifierChanceMultiplier": 1,
    "rareFishChance": 0.2,
    "luckMultiplier": 1,
    "spawnWeight": 100,
    "eventRadius": 15,
    "_source": "variablesjs_5748"
  }
]